{
  "labels": [],
  "comment": "**Disclaimer** Greptiles Reviews use AI, make sure to check over its work",
  "fixWithAI": true,
  "strictness": 1,
  "statusCheck": true,
  "commentTypes": ["syntax", "logic", "style"],
  "instructions": "",
  "disabledLabels": [],
  "excludeAuthors": ["dependabot[bot]", "github-actions[bot]"],
  "ignoreKeywords": "chore(translations)",
  "includeAuthors": [],
  "summarySection": {
    "included": true,
    "collapsible": true,
    "defaultOpen": true
  },
  "excludeBranches": [],
  "includeBranches": [],
  "includeKeywords": "",
  "issuesTableSection": {
    "included": true,
    "collapsible": true,
    "defaultOpen": false
  },
  "confidenceScoreSection": {
    "included": true,
    "collapsible": true,
    "defaultOpen": false
  },
  "sequenceDiagramSection": {
    "included": true,
    "collapsible": true,
    "defaultOpen": false
  },
  "shouldUpdateDescription": true,
  "updateExistingSummaryComment": true
}
